<map>
  <entry>
    <string>artndh</string>
    <org.openmrs.module.reporting.evaluation.parameter.Mapped>
      <parameterizable class="org.openmrs.module.reporting.dataset.definition.SimplePatientDataSetDefinition">
        <name>identifiers</name>
        <parameters/>
        <patientProperties>
          <string>patientId</string>
          <string>age</string>
          <string>gender</string>
          <string>familyName</string>
          <string>givenName</string>
          <string>patientIdentifier</string>
          <string>personAddress</string>
          <string>birthdate</string>
          
        </patientProperties>
        <identifierTypes>
          <patientIdentifierType uuid="18e5329e-a89d-11df-bba5-000c297f1161"/>
        </identifierTypes>
        <programWorkflows>
          <programWorkflowType uuid="18e5329e-a89d-11df-bba5-000c297f1161"/>
        </programWorkflows>
      </parameterizable>
      <parameterMappings/>
    </org.openmrs.module.reporting.evaluation.parameter.Mapped>
  </entry>
</map>