<htmlform formUuid="55ee4b76-1985-456e-8536-0958e7056b6b" formName="Chronic Care Visit"
          formEncounterType="664bb896-977f-11e1-8993-905e29aff6c1" formVersion="1.0">

    <macros>
        <!-- Not used -->
        height=5090
        weight=5089
        systolicBP=5085
        diastolicBP=5086
        nextAppt=5096
    </macros>

    <!-- Flowsheet table view -->
    <ifMode mode="VIEW" include="true">

        <table class="visit-table data-entry-table">
            <thead class="visit-table-header">
                <tr>
                    <td>Visit Date</td>
                    <td>HT</td>
                    <td>WT</td>
                    <td>Blood<br/>Pressure</td>
                    <td>Fingerstick</td> 
                    <td>CHF NYHA<br/>Classification</td>
                    <td># of seizures</td>
                    <td>Peak Flow <br/>/ % of Predicted</td>
                    <td>Asthma<br/>Classification</td>
                    <td>Diagnosis</td>
                    <td>Hospitalized<br/>since last visit?</td>
                    <td>For NCD?</td>
                    <td>Preferred Treatment<br/>Out of stock?</td>
                    <td>Current Medications</td>
                    <td>Medications Changed?</td>
                    <td>Next Appt.</td>
                    <td>High Risk?</td>
                    <td>Visit fully<br/>completed?</td>
                    <td>Comment</td>                  
                </tr>
                <tr style="font-size:.7em;">
                    <td>cm</td>
                    <td>kg</td>
                    <td>mmHg</td>
                    <td>mg/dl</td>
                    <td></td>
                    <td></td>
                    <td>/month</td>
                    <td></td>
                    <td></td>
                    <td></td>
                    <td></td>
                    <td></td>
                    <td></td>
                    <td></td>
                    <td></td>
                    <td></td>
                    <td></td>
                    <td></td>
                    <td></td>
                </tr>

            </thead>
            <tbody class="visit-table-body">
                <tr class="visit-table-row">
                    <td class="nowrap visit-date">
                        <!-- Encounter Date -->
                        <encounterDate/>
                    </td>
                    <td>
                        <!-- Height -->
                        <obsreference conceptId="$height" id="heightEntered" size="3"/>
                    </td>
                    <td>
                        <!-- Weight -->
                        <obsreference conceptId="$weight" id="weightInput" size="3"/>
                    </td>

                    <td>
                        <!-- Blood Pressure -->
                        <obsreference conceptId="$systolicBP" />/<obsreference conceptId="$diastolicBP" />
                    </td>

                    <!-- Fingerstick -->
                    <td>
                        <obs conceptId="887"/> <obs conceptId="6381" answerConceptId="6379" style="checkbox"/>
                    </td>
                    <td>
                        <!-- CHF NYHA Classification --> 
                        <obs conceptId="3139" answerConceptIds="3135,3136,3137,3138" answerLabels="I,II,III,IV" style="radio"/>
                    </td>
                    <td>
                        <!-- # Seizures -->
                        <obs conceptId="7924"/>
                    </td>

                        <!-- Peak flow / percent predicted -->
                    <td><obs conceptId="7925"/> / <obs conceptId="7926"/></td>

                    <td>
                        <!-- Asthma class -->
                        <obs conceptId="8410" answerConceptIds="1905,8405,8406,8407,8408,8409" answerLabels="Not asthma,Intermittent,Mild persistent,Moderate persistent,Severe persistent,Severe Uncontrolled"/>
                    </td>
                    <td>
                        <!-- Diagnosis -->
                        <obs conceptId="3683" answerConceptIds="5,903,155,3720,3468,5622" answerLabels="Asthma,Hypertension,Epilepsy,Diabetes,Heart Failure,Other" style="checkbox"/>
                    </td>
                    <td>
                        <!-- Hospitalized since last visit -->
                        <obs conceptId="1715" style="yes_no" yesLabel="Y" noLabel="N" />
                    </td>
                    <td>
                        <!-- For NCD? -->
                        <obs conceptId="8411" style="radio" answerConceptIds="1066,1065" answerLabels="N,Y" />
                    </td>
                    <td>
                        <!-- Preferred out of stock -->
                        <obs conceptId="8412" style="radio" answerConceptIds="1066,1065" answerLabels="N,Y" />
                    </td>
                    <td>
                        <!-- current meds -->
                        <obs conceptId="1193" answerConceptIds="798,1240,1243,3182,3187,1242,250,3186,3183,254,238,273,920,8413,4052,4046,99,4061" answerLabels="Salbutamol inhaler,Beclomethasone inhaler,Hydrochlorothiazide,Captopril,Amlodipine,Enalapril,Nifedipine,Atenolol,Lisinopril,Propanolol,Phenobarbital,Phenytoin,Carbamazepine,Insulin,Metformin,Glibenclamide,Furosemide,Spironolactone" style="checkbox"/>
                    </td>    
                    <td>
                        <!-- meds changed? -->
                        <obs conceptId="2432" answerConceptIds="1066,1065" answerLabels="N,Y" style="radio"/>
                    </td>              
                    <td>
                        <!-- next appt -->
                        <obsreference conceptId="$nextAppt" id="appointmentDate" allowFutureDates="true" allowOverride="true"/>
                    </td>
                    <td>
                        <!-- high risk --> 
                        <obs conceptId="8398" answerConceptId="1065" answerLabel="Y"/>
                    </td>
                    <td>
                        <!-- fully completed --> 
                        <obs conceptId="8082" style="radio" answerConceptIds="1065,1066,1067" answerLabels="Y,N,Unk"/>
                    </td>
                    <td>
                        <!-- comments --> 
                        <obs conceptId="2922"/>
                    </td>                    
                </tr>
            </tbody>
        </table>

    </ifMode>

    <!-- Data entry view -->
    <ifMode mode="VIEW" include="false">

        <h4 style="font-style: italic;">
            <b>Epilepsy Card</b>
            <span style="padding-left:50px;">Version 1</span>

            <span style="padding-left:50px;">
                <b style="padding-right:10px;">NCD Reg no:</b>
                <b>
                    <lookup complexExpression="#foreach( $id in $patientIdentifiers.get(&quot;Chronic Care Number&quot;) ) $!id #end"/>
                </b>
            </span>
        </h4>

        <table class="visit-edit-table">
            <tr>
                <th>Visit Date</th>
                <td><lookup expression="context.defaultEncounterDate" />
                    <span style="display:none"><encounterDate id="visitDate" size="20" /></span>
                </td>
            </tr>
            <tr>
                <th>Visit Location</th>
                <td>
                    <encounterLocation id="visitLocation"/>
                </td>
            </tr>
            <tr>
                <th>Provider</th>
                <td>
                    <encounterProvider default="16576"/>
                </td>
            </tr>
            <tr>
                <th>Height</th>
                <td class="focus-field">
                    <td class="focus-field"><obsreference conceptId="$height" id="heightInput" showUnits="true"/></td>
                </td>
            </tr>
            <tr>
                <th>Weight</th>
                <td>
                    <obsreference conceptId="$weight" id="weightInput" showUnits="true"/>
                </td>
            </tr>
            <tr>
                <th>Blood Pressure</th>
                <td><obsreference conceptId="$systolicBP" />/<obsreference conceptId="$diastolicBP" /></td>
            </tr>
            <tr>
                <th>Fingerstick (fasting)</th>
                <td>
                    <obs conceptId="887"/> <obs conceptId="6381" answerConceptId="6379" style="checkbox" answerLabel=""/>
                </td>
            </tr>
            <tr>
                <th>CHF NYHA Classification</th>
                <td>
                    <obs conceptId="3139" answerConceptIds="3135,3136,3137,3138" answerLabels="I,II,III,IV" style="radio"/>
                </td>
            </tr>
            <tr>
                <th>Number of seizures<br/>in the last month</th>
                <td>
                    <obs conceptId="7924"/>
                </td>
            </tr>
            <tr>
                <th>Peak Flow (Percent of predicted)</th>
                <td>
                    <obs conceptId="7925"/> (<obs conceptId="7926"/>)
                </td>
            </tr>
            <tr>
                <th>Asthma Classification</th>
                <td>
                    <obs conceptId="8410" answerConceptIds="1905,8405,8406,8407,8408,8409" answerLabels="Not asthma,Intermittent,Mild persistent,Moderate persistent,Severe persistent,Severe Uncontrolled"/>  
                </td>
            </tr>   

            <tr>
                <th>Diagnosis</th>
                <td>
                    <obs conceptId="3683" answerConceptIds="5,903,155,3720,3468,5622" answerLabels="Asthma,Hypertension,Epilepsy,Diabetes,Heart Failure,Other" style="checkbox"/>
                </td>
            </tr>                                  
            <tr>
                <th>Hospitalized since last visit?</th>
                <td>
                    <obs conceptId="1715" style="yes_no"/> 
                </td>
            </tr>   
            <tr>
                <th>For NCD?</th>
                <td>
                    <obs conceptId="8411" style="radio"/> 
                </td>
            </tr>   
            <tr>
                <th>Preferred treatment out of stock?</th>
                <td>
                    <obs conceptId="8412" style="radio"/>
                </td>
            </tr> 
            <tr>
                <th>Asthma Medications</th>
                <td>
                    <obs conceptId="1193" answerConceptId="798" answerLabel="Salbutamol inhaler" style="checkbox"/>
                    <obs conceptId="1193" answerConceptId="1240" answerLabel="Beclomethasone inhaler" style="checkbox"/>
                </td>
            </tr>   
            <tr>
                <th>Hypertension Medications</th>
                <td>
                    <obs conceptId="1193" answerConceptId="1243" answerLabel="Hydrochlorothiazide" style="checkbox"/><br/>
                    <obs conceptId="1193" answerConceptId="3182" answerLabel="Captopril" style="checkbox"/><br/>
                    <obs conceptId="1193" answerConceptId="3187" answerLabel="Amlodipine" style="checkbox"/><br/>
                    <obs conceptId="1193" answerConceptId="1242" answerLabel="Enalapril" style="checkbox"/><br/>
                    <obs conceptId="1193" answerConceptId="250" answerLabel="Nifedipine" style="checkbox"/><br/>
                    <obs conceptId="1193" answerConceptId="3186" answerLabel="Atenolol" style="checkbox"/><br/>
                    <obs conceptId="1193" answerConceptId="3183" answerLabel="Lisinopril" style="checkbox"/><br/>
                    <obs conceptId="1193" answerConceptId="254" answerLabel="Propanolol" style="checkbox"/>
                </td>
            </tr>  
            <tr>
                <th>Epilepsy Medications</th>
                <td>
                    <obs conceptId="1193" answerConceptId="238" answerLabel="Phenobarbital" style="checkbox"/><br/>
                    <obs conceptId="1193" answerConceptId="273" answerLabel="Phenytoin" style="checkbox"/><br/>
                    <obs conceptId="1193" answerConceptId="920" answerLabel="Carbamazepine" style="checkbox"/><br/>
                </td>
            </tr>  
            <tr>
                <th>Diabetes Medications</th>
                <td>
                    <obs conceptId="1193" answerConceptId="8413" answerLabel="Insulin" style="checkbox"/><br/>
                    <obs conceptId="1193" answerConceptId="4052" answerLabel="Metformin" style="checkbox"/><br/>
                    <obs conceptId="1193" answerConceptId="4046" answerLabel="Glibenclamide" style="checkbox"/>
                </td>
            </tr>     
            <tr>
                <th>Heart Failure Medications</th>
                <td>
                    <obs conceptId="1193" answerConceptId="99" answerLabel="Furosemide" style="checkbox"/>
                    <obs conceptId="1193" answerConceptId="4061" answerLabel="Spironolactone" style="checkbox"/>
                </td>
            </tr>                                   
            <tr>
                <th>Medications changed?</th>
                <td>
                    <obs conceptId="2432" answerConceptIds="1066,1065" answerLabels="No,Yes" style="radio"/>
                </td>
            </tr>            
            <tr>
                <th>Next appointment</th>
                <td>
                    <obsreference conceptId="$nextAppt" id="appointmentDate" allowFutureDates="true" allowOverride="true"/>
                </td>
            </tr>
            <tr>
                <th>Visit fully completed?</th>
                <td>
                    <obs conceptId="8082" style="radio" answerConceptIds="1065,1066,1067"/>
                </td>
            </tr>            
            <tr>
                <th>Comment (if not fully completed)</th>
                <td>
                    <obs conceptId="2922"/>
                </td>
            </tr>     
        </table>

        <submit/>

    </ifMode>

</htmlform>
